pangeamt_nlp/__init__.py
pangeamt_nlp/seg.py
pangeamt_nlp/tu.py
pangeamt_nlp/types.py
pangeamt_nlp/bin/debug_normalizers.py
pangeamt_nlp/bpe/__init__.py
pangeamt_nlp/bpe/bpe.py
pangeamt_nlp/bpe/sentencepiece.py
pangeamt_nlp/data_batcher/__init__.py
pangeamt_nlp/data_batcher/batcher.py
pangeamt_nlp/locale/__init__.py
pangeamt_nlp/locale/lang.py
pangeamt_nlp/locale/locale.py
pangeamt_nlp/multilingual_resource/__init__.py
pangeamt_nlp/multilingual_resource/multilingual_resource_base.py
pangeamt_nlp/multilingual_resource/af/__init__.py
pangeamt_nlp/multilingual_resource/af/af.py
pangeamt_nlp/multilingual_resource/af/af_header.py
pangeamt_nlp/multilingual_resource/af/af_reader.py
pangeamt_nlp/multilingual_resource/bilingual/__init__.py
pangeamt_nlp/multilingual_resource/bilingual/bilingual.py
pangeamt_nlp/multilingual_resource/bilingual/bilingual_reader.py
pangeamt_nlp/multilingual_resource/converter/__init__.py
pangeamt_nlp/multilingual_resource/converter/af2tmx.py
pangeamt_nlp/multilingual_resource/converter/afraw2af.py
pangeamt_nlp/multilingual_resource/dataset/__init__.py
pangeamt_nlp/multilingual_resource/dataset/dataset.py
pangeamt_nlp/multilingual_resource/dataset/dataset_reader.py
pangeamt_nlp/multilingual_resource/dataset/dataset_reader_bilingual.py
pangeamt_nlp/multilingual_resource/tmx/__init__.py
pangeamt_nlp/multilingual_resource/tmx/tmx.py
pangeamt_nlp/multilingual_resource/tmx/tmx_reader_base.py
pangeamt_nlp/multilingual_resource/tmx/tmx_reader_bilingual.py
pangeamt_nlp/multilingual_resource/tmx/tmx_writter.py
pangeamt_nlp/multilingual_resource/xliff/__init__.py
pangeamt_nlp/multilingual_resource/xliff/xliff.py
pangeamt_nlp/multilingual_resource/xliff/xliff_reader_bilingual.py
pangeamt_nlp/processor/__init__.py
pangeamt_nlp/processor/pipeline_decoding.py
pangeamt_nlp/processor/pipeline_training.py
pangeamt_nlp/processor/processor_factory.py
pangeamt_nlp/processor/base/__init__.py
pangeamt_nlp/processor/base/normalizer_base.py
pangeamt_nlp-1.0.78.5.dist-info/METADATA
pangeamt_nlp-1.0.78.5.dist-info/WHEEL
pangeamt_nlp-1.0.78.5.dist-info/top_level.txt
pangeamt_nlp-1.0.78.5.dist-info/RECORD
