Metadata-Version: 2.4
Name: pangeamt-nlp
Version: 1.0.78.5
Summary: h1 align="center">
Author: Pangeamt
Requires-Dist: OpenNMT-py
Requires-Dist: neologdn
Requires-Dist: Click
Requires-Dist: lxml
Requires-Dist: mecab-python3
Requires-Dist: pycld2
Requires-Dist: PyYAML
Requires-Dist: sacremoses
Requires-Dist: subword_nmt
Requires-Dist: regex
Requires-Dist: alphabet-detector
Requires-Dist: Cython
Requires-Dist: wheel
Requires-Dist: twine
Requires-Dist: setuptools
Requires-Dist: pycld3
Requires-Dist: prettytable
Requires-Dist: pycnnum
Requires-Dist: thai_segmenter
Requires-Dist: jieba
Requires-Dist: sentencepiece
Requires-Dist: keyring
Requires-Dist: Babel
Dynamic: author
Dynamic: description
Dynamic: description-content-type
Dynamic: requires-dist
Dynamic: summary
